Metadata-Version: 2.1
Name: inline-model-metrics
Version: 0.1.3
Summary: inline_model_metrics is a package to to run model metrics inline with a climate model.
Home-page: https://github.com/MetOffice/inline_model_metrics
Download-URL: https://github.com/MetOffice/inline_model_metrics/releases
Author: Met Office
Author-email: jon.seddon@metoffice.gov.uk
License: BSD 3-Clause License
Keywords: climate,tracking,inline
Classifier: Development Status :: 5 - Production/Stable
Classifier: License :: OSI Approved :: BSD License
Classifier: Natural Language :: English
Classifier: Topic :: Scientific/Engineering :: Atmospheric Science
Classifier: Programming Language :: Python :: 3.6
Classifier: Programming Language :: Python :: 3.7
Classifier: Programming Language :: Python :: 3.8
Classifier: Programming Language :: Python :: 3.9
License-File: LICENSE
